landcover_assignment/__init__.py
landcover_assignment/afforestation.py
landcover_assignment/database/__init__.py
landcover_assignment/database/land_use_database.db
landcover_assignment/distribution.py
landcover_assignment/geo_landcover_assignment/__init__.py
landcover_assignment/geo_landcover_assignment/catchment_landcover.py
landcover_assignment/geo_landcover_assignment/geo_afforestation.py
landcover_assignment/geo_landcover_assignment/geo_distribution.py
landcover_assignment/geo_landcover_assignment/geo_landcover.py
landcover_assignment/geo_landcover_assignment/geo_transition_matrix.py
landcover_assignment/landcover.py
landcover_assignment/national_landcover.py
landcover_assignment/optimisation/__init__.py
landcover_assignment/optimisation/landcover_optimisation.py
landcover_assignment/resource_manager/__init__.py
landcover_assignment/resource_manager/data_loader.py
landcover_assignment/resource_manager/database_manager.py
landcover_assignment/resource_manager/landcover_data_manager.py
landcover_assignment/resource_manager/scenario_data_fetcher.py
landcover_assignment/resource_manager/transition_data_fetcher.py
landcover_assignment/transition_matrix.py
landcover_assignment-0.4.0.dist-info/LICENSE
landcover_assignment-0.4.0.dist-info/METADATA
landcover_assignment-0.4.0.dist-info/WHEEL
landcover_assignment-0.4.0.dist-info/RECORD
