Metadata-Version: 2.1
Name: landcover_assignment
Version: 0.4.0
Summary: A goblin tool for the generation of areas of alternative land uses based on spared area available
License: MIT
Author: Colm Duffy
Requires-Python: >=3.9,<4.0
Classifier: License :: OSI Approved :: MIT License
Classifier: Programming Language :: Python :: 3
Classifier: Programming Language :: Python :: 3.9
Classifier: Programming Language :: Python :: 3.10
Classifier: Programming Language :: Python :: 3.11
Classifier: Programming Language :: Python :: 3.12
Requires-Dist: catchment_data_api (>=0.1.0,<0.2.0)
Requires-Dist: cplex (>=22.1.2.0,<23.0.0.0)
Requires-Dist: numpy (>=1.25.0,<2.0.0)
Requires-Dist: pandas (==2.1.4)
Requires-Dist: pyomo (>=6.8.0,<7.0.0)
Requires-Dist: sqlalchemy (>=1.4.0,<2.0.0)
